{"start.md":"BNGcKTl9","classified_ts_extends.md":"CHwEDLso","classified_css_color-opacity.md":"Cbie8eGR","classified_electron_print-error.md":"CkbbRQYI","unclassified_common_nodejs.md":"B8-SSeai","unclassified_sundry_pnpm-monorepo.md":"BvZAatmV","unclassified_sundry_uninstall-vscode.md":"6KDFvyij","classified_ts_expand.md":"esYUqSdZ","index.md":"2Gj2uckE","classified_ts_promise-error.md":"DYFUqMi2","unclassified_common_wsl.md":"CqQZ9Lzg","classified_ts_tsconfig-json.md":"D_QIb4X4","classified_ts_assertion.md":"DaQv7DTx","classified_ts_type-predicate-function.md":"B3vSL0cm","classified_ts_filter.md":"CQMh4T6v","unclassified_common_stylelint.md":"BMdLRZkP","api-examples.md":"BWj8DiKm","classified_ts_types.md":"Cdr97b7R","classified_electron_ipcrenderer-error.md":"DWPfXZ72","unclassified_common_eslint.md":"C170_qhd","markdown-examples.md":"0N4iSjgN","classified_node_recommend.md":"BpClOanL","unclassified_sundry_ruoyi-sort.md":"BaFxKaZ4","classified_electron_build-options.md":"CGB4GmPN","classified_electron_error.md":"BB4I32b-","unclassified_sundry_chrome-kiosk-printing.md":"DIrOG24U","unclassified_sundry_vscode-cmder.md":"uhpUfdVt","unclassified_common_git.md":"BNN5Eev7","classified_code_is.md":"BeXyY0UX","classified_js_modules.md":"hDXUymuE","classified_js_element.md":"DvGo-rCU","classified_js_cesium-overlay.md":"DgPU6436","unclassified_sundry_homework.md":"hUXN6W79","classified_js_cesium-weather-effect.md":"BMDP79Jx","classified_code_usecache.md":"CVjxPHA9","unclassified_common_eslint-vue3.md":"CbyjASpt"}
